sandlerprops/__init__.py
sandlerprops/cli.py
sandlerprops/compound.py
sandlerprops/properties.py
sandlerprops/resources/data/README.md
sandlerprops/resources/data/properties_database.csv
sandlerprops-0.5.0.dist-info/METADATA
sandlerprops-0.5.0.dist-info/WHEEL
sandlerprops-0.5.0.dist-info/entry_points.txt
sandlerprops-0.5.0.dist-info/licenses/LICENSE
sandlerprops-0.5.0.dist-info/RECORD
