Metadata-Version: 2.4
Name: sandlerprops
Version: 0.5.0
Summary: A python interface to the pure-component properties database for Sandler 5e
Author-email: Cameron F Abrams <cfa22@drexel.edu>
License-File: LICENSE
Classifier: License :: OSI Approved :: MIT License
Classifier: Programming Language :: Python :: 3
Requires-Python: >=3.7
Requires-Dist: numpy
Requires-Dist: pandas
Requires-Dist: pint
